uzbot.py
uzbot-0.0.1.dist-info/METADATA
uzbot-0.0.1.dist-info/WHEEL
uzbot-0.0.1.dist-info/RECORD
